unicodecheck/__init__.py
unicodecheck/__main__.py
unicodecheck/args.py
unicodecheck/cli.py
unicodecheck/core.py
unicodecheck/py.typed
unicodecheck-1.2.5.dist-info/licenses/LICENSE
unicodecheck-1.2.5.dist-info/METADATA
unicodecheck-1.2.5.dist-info/WHEEL
unicodecheck-1.2.5.dist-info/entry_points.txt
unicodecheck-1.2.5.dist-info/top_level.txt
unicodecheck-1.2.5.dist-info/RECORD
