Metadata-Version: 2.4
Name: unicodecheck
Version: 1.2.5
Summary: Check if Unicode text files are Unicode-normalized
Maintainer-email: curegit <contact@curegit.jp>
License-Expression: MIT
Project-URL: homepage, https://github.com/curegit/unicodecheck
Project-URL: repository, https://github.com/curegit/unicodecheck.git
Keywords: Unicode,character encoding
Classifier: Programming Language :: Python :: 3 :: Only
Classifier: Operating System :: OS Independent
Classifier: Topic :: Text Processing
Classifier: Typing :: Typed
Requires-Python: >=3.11
License-File: LICENSE
Requires-Dist: chardet
Requires-Dist: rich
Provides-Extra: dev
Requires-Dist: pip; extra == "dev"
Requires-Dist: build; extra == "dev"
Requires-Dist: twine; extra == "dev"
Requires-Dist: black; extra == "dev"
Requires-Dist: mypy; extra == "dev"
Dynamic: license-file
